gradient_chat/__init__.py
gradient_chat/client.py
gradient_chat/conversation.py
gradient_chat/headers.py
gradient_chat_client-0.1.0.dist-info/licenses/LICENSE
gradient_chat_client-0.1.0.dist-info/METADATA
gradient_chat_client-0.1.0.dist-info/WHEEL
gradient_chat_client-0.1.0.dist-info/top_level.txt
gradient_chat_client-0.1.0.dist-info/RECORD
