Metadata-Version: 2.4
Name: gradient-chat-client
Version: 0.1.0
Summary: Unofficial Python client for Gradient Chat (supports gpt-oss-120b and qwen3-235b)
Author: abswn
License: MIT License
Project-URL: Homepage, https://github.com/abswn/gradient-chat-python
Keywords: gradient,gradient-api,gpt,qwen3,gpt-oss-120b,qwen3-235b
Classifier: Development Status :: 5 - Production/Stable
Classifier: Intended Audience :: Developers
Classifier: License :: OSI Approved :: MIT License
Classifier: Programming Language :: Python :: 3.9
Classifier: Programming Language :: Python :: 3.10
Classifier: Programming Language :: Python :: 3.11
Classifier: Programming Language :: Python :: 3.12
Classifier: Programming Language :: Python :: 3.13
Classifier: Programming Language :: Python :: Implementation :: CPython
Classifier: Programming Language :: Python :: Implementation :: PyPy
Classifier: Topic :: Software Development :: Libraries
Classifier: Topic :: Scientific/Engineering :: Artificial Intelligence
Classifier: Topic :: Internet :: WWW/HTTP :: Dynamic Content
Requires-Python: >=3.9
License-File: LICENSE
Requires-Dist: requests
Requires-Dist: fake-useragent
Dynamic: license-file
